passsssword.py
passsssword-0.1.0.dist-info/LICENSE
passsssword-0.1.0.dist-info/METADATA
passsssword-0.1.0.dist-info/WHEEL
passsssword-0.1.0.dist-info/RECORD
