Metadata-Version: 2.1
Name: Passsssword
Version: 0.1.0
Summary: Utilize 1Password vault data with Python decorators and context managers. Driven by the 1Password CLI interface. 🐍🔐
License: MIT
Author: Chris Lemke
Author-email: 1@lemke.ai
Requires-Python: >=3.8,<4.0
Classifier: License :: OSI Approved :: MIT License
Classifier: Programming Language :: Python :: 3
Classifier: Programming Language :: Python :: 3.8
Classifier: Programming Language :: Python :: 3.9
Classifier: Programming Language :: Python :: 3.10
Classifier: Programming Language :: Python :: 3.11
Requires-Dist: python-dotenv (>=1.0.0,<2.0.0)
